[
  {
    "description": "  Testing BDD",
    "keyword": "Feature",
    "name": "Example Test",
    "line": 1,
    "id": "example-test",
    "tags": [],
    "uri": "example.feature",
    "elements": [
      {
        "id": "example-test;truthly-value-is-true",
        "keyword": "Scenario",
        "line": 4,
        "name": "Truthly value is true",
        "tags": [],
        "type": "scenario",
        "steps": [
          {
            "arguments": [],
            "keyword": "Given ",
            "line": 5,
            "name": "I am on \"home page\"",
            "result": {
              "status": "undefined"
            }
          },
          {
            "arguments": [],
            "keyword": "When ",
            "line": 6,
            "name": "I view the page from \"iphone6\"",
            "result": {
              "status": "skipped"
            }
          },
          {
            "arguments": [],
            "keyword": "Then ",
            "line": 9,
            "name": "A truthy value is true",
            "result": {
              "status": "skipped"
            }
          }
        ]
      }
    ]
  }
]